{
  "globals": {
    "__DEV__": true
  },
  "moduleNameMapper": {
    "\\.(jpg|jpeg|png|gif|eot|otf|webp|svg|ttf|woff|woff2|mp4|webm|wav|mp3|m4a|aac|oga)$": "<rootDir>/__mocks__/fileMock.js",
    "\\.(css|less)$": "<rootDir>/__mocks__/styleMock.js",
    "^react-native(.*)$": "react-native-web"
  },
  "testPathIgnorePatterns": [
    "/node_modules/",
    "/*.android.jsx?",
    "/*.windows.jsx?",
    "/*.macos.jsx?",
    "/*.ios.jsx?"
  ],
  "transform": {
    "^.+\\.js$": "<rootDir>/jest/transformer.web.js"
  },
  "transformIgnorePatterns": [
    "node_modules/(?!react-native|react-navigation)"
  ]
}